README.rst
setup.py
parsecpy/__init__.py
parsecpy/_common.py
parsecpy/createinputs.py
parsecpy/csa.py
parsecpy/dataprocess.py
parsecpy/model.py
parsecpy/processlogs.py
parsecpy/pso.py
parsecpy/runmodel.py
parsecpy/runmodel_errors.py
parsecpy/runprocess.py
parsecpy.egg-info/PKG-INFO
parsecpy.egg-info/SOURCES.txt
parsecpy.egg-info/dependency_links.txt
parsecpy.egg-info/entry_points.txt
parsecpy.egg-info/not-zip-safe
parsecpy.egg-info/requires.txt
parsecpy.egg-info/top_level.txt