Metadata-Version: 1.1
Name: parsecpy
Version: 1.0.4
Summary: Parsec Benchmark interface tool
Home-page: https://github.com/alexfurtunatoifrn/parsecpy
Author: Alex Furtunato
Author-email: alexfurtunato@gmail.com
License: MIT
Keywords: parsec benchmark tool
Platform: UNKNOWN
Classifier: Development Status :: 3 - Alpha
Classifier: Topic :: Software Development :: Build Tools
Classifier: Topic :: Software Development :: Libraries :: Python Modules
Classifier: Topic :: Scientific/Engineering
Classifier: License :: OSI Approved :: MIT License
Classifier: Programming Language :: Python :: 3
